clashnetlib/__init__.py
clashnetlib/decision_maker.py
clashnetlib/implements/__init__.py
clashnetlib/implements/fight_decision_maker.py
clash_net_lib-0.0.1.dist-info/LICENSE
clash_net_lib-0.0.1.dist-info/METADATA
clash_net_lib-0.0.1.dist-info/WHEEL
clash_net_lib-0.0.1.dist-info/RECORD
